setup.py
aspose_words_java_for_python.egg-info/PKG-INFO
aspose_words_java_for_python.egg-info/SOURCES.txt
aspose_words_java_for_python.egg-info/dependency_links.txt
aspose_words_java_for_python.egg-info/top_level.txt
loadingandsaving/__init__.py
mailmergeandreporting/__init__.py
programmingwithdocuments/__init__.py
quickstart/__init__.py