Metadata-Version: 1.1
Name: aspose-words-java-for-python
Version: 1.0.0
Summary: Aspose.Words Java for Python
Home-page: https://github.com/asposewords/Aspose_Words_Java/tree/master/Plugins/Aspose_Words_Java_for_Python
Author: Fahad Adeel
Author-email: fahadadeel@gmail.com
License: UNKNOWN
Platform: UNKNOWN
Classifier: Programming Language :: Python
Classifier: Programming Language :: Python :: 2
Classifier: License :: OSI Approved :: MIT License
Classifier: Operating System :: OS Independent
